RobHelpFunc/__init__.py
RobHelpFunc/myBootstrapping.py
RobHelpFunc-0.0.1.dist-info/LICENSE
RobHelpFunc-0.0.1.dist-info/METADATA
RobHelpFunc-0.0.1.dist-info/WHEEL
RobHelpFunc-0.0.1.dist-info/top_level.txt
RobHelpFunc-0.0.1.dist-info/RECORD
