Metadata-Version: 2.1
Name: RobHelpFunc
Version: 0.0.1
Summary: A collection of helper functions
Home-page: https://github.com/UzumymW839/RobHelpFunc
Author: Robert Metzger
License: GNU
License-File: LICENSE
Requires-Dist: pandas >=2.1.1
Requires-Dist: numpy >=1.26.1
Requires-Dist: matplotlib >=3.8.0
Requires-Dist: scikit-learn >=1.3.1
Requires-Dist: scipy >=1.11.3
